{
    "data": [
        {
            "name": "Bogaert SCA",
            "phone": "+32 50 64 68 62",
            "email": "marie34@daems.net",
            "website": "www.daems.net",
            "location": "Brugge"
        },
        {
            "name": "Thomas BVBA",
            "phone": "+32 9 654 97 31 64",
            "email": "tess.claessens@charlier.org",
            "website": "www.charlier.org",
            "location": "Gent"
        },
        {
            "name": "Dogan NV",
            "phone": "+32 3 678 64 31",
            "email": "diallo.noor@guillaume.org",
            "website": "www.guillaume.org",
            "location": "Antwerpen"
        },
        {
            "name": "Ceulemans Associations",
            "phone": "+32 11 98 76 54",
            "email": "relamrani@yildirim.net",
            "website": "www.yildirim.net",
            "location": "Hasselt"
        },
        {
            "name": "Simons BV",
            "phone": "+32 4 687 64 32",
            "email": "mohammed25@dumont.be",
            "website": "www.dumont.be",
            "location": "Luik"
        },
        {
            "name": "Bogaert SA",
            "phone": "+32 81 31 54 56",
            "email": "janne83@christiaens.com",
            "website": "www.christiaens.com",
            "location": "Namen"
        },
        {
            "name": "Wuyts Group SA",
            "phone": "+32 63 64 97 64 ",
            "email": "eva59@schmitz.org",
            "website": "www.schmitz.org",
            "location": "Arlon"
        },
        {
            "name": "Marchal SA",
            "phone": "+32 65 68 41 32",
            "email": "masson.noa@lemaire.com",
            "website": "www.lemaire.com",
            "location": "Bergen"
        },
        {
            "name": "Timmermans NV",
            "phone": "+32 16 69 31 14",
            "email": "dpierre@gilson.org",
            "website": "www.gilson.org",
            "location": "Leuven"
        },
        {
            "name": "Poncelet SA",
            "phone": "+32 10 63 32 11",
            "email": "mats20@deridder.be",
            "website": "www.deridder.be",
            "location": "Waver"
        }
    ]
}
